semvercli/__init__.py
semvercli/cli.py
semvercli/meta.py
semvercli/semvercli.py
semvercli-0.1.4.dist-info/DESCRIPTION.rst
semvercli-0.1.4.dist-info/METADATA
semvercli-0.1.4.dist-info/RECORD
semvercli-0.1.4.dist-info/WHEEL
semvercli-0.1.4.dist-info/entry_points.txt
semvercli-0.1.4.dist-info/metadata.json
semvercli-0.1.4.dist-info/top_level.txt
