Metadata-Version: 2.0
Name: semvercli
Version: 0.1.4
Summary: basic CLI for python-semver
Home-page: https://github.com/matchdav/semvercli
Author: matthew davidson
Author-email: matthew.davidson@ingrooves.com
License: UNKNOWN
Keywords: semvercli
Platform: UNKNOWN
Classifier: Development Status :: 2 - Pre-Alpha
Classifier: Intended Audience :: Developers
Classifier: Natural Language :: English
Classifier: Programming Language :: Python :: 2
Classifier: Programming Language :: Python :: 2.6
Classifier: Programming Language :: Python :: 2.7
Classifier: Programming Language :: Python :: 3
Classifier: Programming Language :: Python :: 3.3
Classifier: Programming Language :: Python :: 3.4
Classifier: Programming Language :: Python :: 3.5
Requires-Dist: Click (>=6.0)
Requires-Dist: semver (>=2.0)
